{
  "formatVersion": 1,
  "database": {
    "version": 1,
    "identityHash": "a576c0f26540b6150894f9e9a5433524",
    "entities": [
      {
        "tableName": "favorites",
        "createSql": "CREATE TABLE IF NOT EXISTS `${TABLE_NAME}` (`url` TEXT NOT NULL, `title` TEXT NOT NULL, `description` TEXT NOT NULL, `imageUrl` TEXT, `publishedAt` TEXT NOT NULL, PRIMARY KEY(`url`))",
        "fields": [
          {
            "fieldPath": "url",
            "columnName": "url",
            "affinity": "TEXT",
            "notNull": true
          },
          {
            "fieldPath": "title",
            "columnName": "title",
            "affinity": "TEXT",
            "notNull": true
          },
          {
            "fieldPath": "description",
            "columnName": "description",
            "affinity": "TEXT",
            "notNull": true
          },
          {
            "fieldPath": "imageUrl",
            "columnName": "imageUrl",
            "affinity": "TEXT"
          },
          {
            "fieldPath": "publishedAt",
            "columnName": "publishedAt",
            "affinity": "TEXT",
            "notNull": true
          }
        ],
        "primaryKey": {
          "autoGenerate": false,
          "columnNames": [
            "url"
          ]
        }
      }
    ],
    "setupQueries": [
      "CREATE TABLE IF NOT EXISTS room_master_table (id INTEGER PRIMARY KEY,identity_hash TEXT)",
      "INSERT OR REPLACE INTO room_master_table (id,identity_hash) VALUES(42, 'a576c0f26540b6150894f9e9a5433524')"
    ]
  }
}